csvsheet/__init__.py
"csvsheet/__init__.py,cover"
csvsheet/csvsheet.py
"csvsheet/csvsheet.py,cover"
csvsheet-0.1.2.dist-info/LICENSE.txt
csvsheet-0.1.2.dist-info/METADATA
csvsheet-0.1.2.dist-info/WHEEL
csvsheet-0.1.2.dist-info/entry_points.txt
csvsheet-0.1.2.dist-info/top_level.txt
csvsheet-0.1.2.dist-info/RECORD
