Metadata-Version: 2.1
Name: csvsheet
Version: 0.1.2
Summary: Simple formula support for CSV
Home-page: https://github.com/jtplaarj/csvsheet/
Author: Jesús Lázaro
Author-email: jesus.lazaro@ehu.eus
License: MIT
Project-URL: Documentation, https://csvsheet.readthedocs.io/en/latest/
Project-URL: Source, https://github.com/jtplaarj/csvsheet/
Project-URL: Changelog, https://github.com/jtplaarj/csvsheet/blob/master/CHANGELOG.rst
Project-URL: Download, https://pypi.org/project/csvsheet/#files
Platform: any
Classifier: Development Status :: 4 - Beta
Classifier: Programming Language :: Python
License-File: LICENSE.txt
Requires-Dist: importlib-metadata ; python_version < "3.8"
Provides-Extra: testing
Requires-Dist: setuptools ; extra == 'testing'
Requires-Dist: pytest ; extra == 'testing'
Requires-Dist: hypothesis ; extra == 'testing'
Requires-Dist: pytest-cov ; extra == 'testing'
Requires-Dist: pytest-mock ; extra == 'testing'
Requires-Dist: faker ; extra == 'testing'
